pymento/__init__.py
pymento/google_bak01.py
pymento/s3_bak.py
pymento-0.0.3.dist-info/LICENSE
pymento-0.0.3.dist-info/METADATA
pymento-0.0.3.dist-info/WHEEL
pymento-0.0.3.dist-info/top_level.txt
pymento-0.0.3.dist-info/RECORD
