Metadata-Version: 2.1
Name: pymento
Version: 0.0.3
Summary: Backup of stuff I'd like to keep around.
Home-page: https://github.com/thorwhalen/newut/tree/master/pymento
Author: Thor Whalen
License: mit
Platform: any
License-File: LICENSE
